{
"type": "FeatureCollection",
"crs": { "type": "name", "properties": { "name": "urn:ogc:def:crs:OGC:1.3:CRS84" } },
                                                                                
"features": [
{ "type": "Feature", "properties": { "Name": "Deepwater Horizon",
"Image": "", 
"EPA": "<a href='' target='_blank'>EPA facility report</a>", 
"website": "Link to <a href='' target='_blank'>company website</a>", 
"Notes": "." }, 
"geometry": { "type": "Point", "coordinates": [ -88.3871611, 28.7366694 ] } }
]
}
